ifm_contrib/__init__.py
ifm_contrib/_version.py
ifm_contrib/c/__init__.py
ifm_contrib/c/files/__init__.py
ifm_contrib/c/files/database/__init__.py
ifm_contrib/c/files/database/pow.py
ifm_contrib/c/files/feflow/dar.py
ifm_contrib/c/files/xml/PointGroup3D.py
ifm_contrib/c/obj/TimeSeries.py
ifm_contrib/c/obj/__init__.py
ifm_contrib/c/simulator/Simulator.py
ifm_contrib/c/tools/__init__.py
ifm_contrib/colormaps/__init__.py
ifm_contrib/colormaps/feflow_black_blue.xml
ifm_contrib/colormaps/feflow_black_green.xml
ifm_contrib/colormaps/feflow_black_red.xml
ifm_contrib/colormaps/feflow_blue_green_red.xml
ifm_contrib/colormaps/feflow_blue_green_yellow_red.xml
ifm_contrib/colormaps/feflow_classic.xml
ifm_contrib/colormaps/feflow_clear_blue.xml
ifm_contrib/colormaps/feflow_clear_green.xml
ifm_contrib/colormaps/feflow_clear_red.xml
ifm_contrib/colormaps/feflow_clear_white.xml
ifm_contrib/colormaps/feflow_rainbow.xml
ifm_contrib/colormaps/feflow_white_black.xml
ifm_contrib/colormaps/feflow_white_blue.xml
ifm_contrib/colormaps/feflow_white_green.xml
ifm_contrib/colormaps/feflow_white_red.xml
ifm_contrib/colormaps/readme.md
ifm_contrib/contrib_lib/__init__.py
ifm_contrib/contrib_lib/bdgt.py
ifm_contrib/contrib_lib/bdgt_pandas.py
ifm_contrib/contrib_lib/content.py
ifm_contrib/contrib_lib/content_pandas.py
ifm_contrib/contrib_lib/dfe.py
ifm_contrib/contrib_lib/dfe_pandas.py
ifm_contrib/contrib_lib/diag.py
ifm_contrib/contrib_lib/hist.py
ifm_contrib/contrib_lib/hist_pandas.py
ifm_contrib/contrib_lib/mesh.py
ifm_contrib/contrib_lib/mesh_geopandas.py
ifm_contrib/contrib_lib/mesh_pandas.py
ifm_contrib/contrib_lib/obs.py
ifm_contrib/contrib_lib/obs_geopandas.py
ifm_contrib/contrib_lib/particles.py
ifm_contrib/contrib_lib/plot.py
ifm_contrib/contrib_lib/plot_folium.py
ifm_contrib/contrib_lib/plot_geopandas.py
ifm_contrib/contrib_lib/sel.py
ifm_contrib/contrib_lib/sel_pandas.py
ifm_contrib/contrib_lib/settings.py
ifm_contrib/contrib_lib/settings_pandas.py
ifm_contrib-0.2.4.dist-info/LICENSE
ifm_contrib-0.2.4.dist-info/METADATA
ifm_contrib-0.2.4.dist-info/WHEEL
ifm_contrib-0.2.4.dist-info/top_level.txt
ifm_contrib-0.2.4.dist-info/RECORD
