Metadata-Version: 2.1
Name: ifm_contrib
Version: 0.2.4
Summary: *ifm_contrib* is an Open-Source Extension of the IFM, the Python API of the groundwater modellierung software [FEFLOW](https://en.wikipedia.org/wiki/FEFLOW) by [DHI](https://www.dhigroup.com).
Author-email: Alexander Renz <alex.renz@gmx.net>
License: MIT
Project-URL: Bug Tracker, https://github.com/red5alex/ifm_contrib/issues
Project-URL: Source Code, https://github.com/red5alex/ifm_contrib
Requires-Python: <3.13
License-File: LICENSE
Requires-Dist: geopandas
Requires-Dist: matplotlib
Requires-Dist: numpy
Requires-Dist: pandas
Requires-Dist: shapely
Provides-Extra: test
Requires-Dist: pytest; extra == "test"
Provides-Extra: doc
Requires-Dist: sphinx; extra == "doc"
Requires-Dist: sphinx_rtd_theme; extra == "doc"
Requires-Dist: sphinxcontrib-apidoc; extra == "doc"
Requires-Dist: ipython; extra == "doc"
Requires-Dist: ipywidgets; extra == "doc"
